{
  "python.linting.enabled": true,
  "python.linting.pylintEnabled": false,
  "python.linting.flake8Enabled": true,
  "python.linting.mypyEnabled": false,
  "python.formatting.provider": "black",
  "diagnostic.enable":~,
  "diagnostic.virtualText": true,
  "diagnostic.checkCurrentLine": false,
  "diagnostic.virtualTextCurrentLineOnly": false,
  "diagnostic.virtualTextPrefix": " 🧠 ",
  "diagnostic.errorSign": "✖",
  "diagnostic.warningSign": "⚠",
  "diagnostic.infoSign": "●",
  "diagnostic.hintSign": "○",
  "python.pythonPath": "~/.pyenv/shims/python3",
  "python.venvPath": "~/.pyenv/versions/3.7.7"
}
